trialcalculator/__init__.py
trialcalculator-0.1.dist-info/LICENSE.txt
trialcalculator-0.1.dist-info/METADATA
trialcalculator-0.1.dist-info/WHEEL
trialcalculator-0.1.dist-info/top_level.txt
trialcalculator-0.1.dist-info/RECORD
