Metadata-Version: 2.1
Name: trialcalculator
Version: 0.1
Summary: Basic calculator
Author: DESHANA PARIKH
Author-email: deshana.parikh@crestdatasys.com
Classifier: Programming Language :: Python :: 3
Classifier: License :: OSI Approved :: MIT License
Classifier: Operating System :: OS Independent
License-File: LICENSE.txt
